README.md
setup.cfg
setup.py
basecampy3R/__init__.py
basecampy3R/__version__.py
basecampy3R/bc3_api.py
basecampy3R/bc3_cli.py
basecampy3R/config.py
basecampy3R/constants.py
basecampy3R/dictionary_cache.py
basecampy3R/exc.py
basecampy3R/rated_semaphore.py
basecampy3R/response_cache.py
basecampy3R/token_requestor.py
basecampy3R/transport_adapter.py
basecampy3R.egg-info/PKG-INFO
basecampy3R.egg-info/SOURCES.txt
basecampy3R.egg-info/dependency_links.txt
basecampy3R.egg-info/entry_points.txt
basecampy3R.egg-info/not-zip-safe
basecampy3R.egg-info/requires.txt
basecampy3R.egg-info/top_level.txt
basecampy3R/endpoints/__init__.py
basecampy3R/endpoints/_base.py
basecampy3R/endpoints/answers.py
basecampy3R/endpoints/campfire_lines.py
basecampy3R/endpoints/campfires.py
basecampy3R/endpoints/message_boards.py
basecampy3R/endpoints/message_categories.py
basecampy3R/endpoints/messages.py
basecampy3R/endpoints/people.py
basecampy3R/endpoints/project_constructions.py
basecampy3R/endpoints/projects.py
basecampy3R/endpoints/recordings.py
basecampy3R/endpoints/templates.py
basecampy3R/endpoints/todolist_groups.py
basecampy3R/endpoints/todolists.py
basecampy3R/endpoints/todos.py
basecampy3R/endpoints/todosets.py
basecampy3R/endpoints/util.py