Metadata-Version: 2.1
Name: basecampy3R
Version: 0.2.2
Summary: Aims to be the easiest to use version of the Basecamp 3 API
Home-page: https://github.com/phistrom/basecampy3
Author: Rostislav Misiura
Author-email: rostislav9999@gmail.com
License: MIT
Platform: UNKNOWN
Classifier: Development Status :: 4 - Beta
Classifier: Intended Audience :: Developers
Classifier: Natural Language :: English
Classifier: License :: OSI Approved :: MIT License
Classifier: Programming Language :: Python
Classifier: Programming Language :: Python :: 2
Classifier: Programming Language :: Python :: 2.7
Classifier: Programming Language :: Python :: 3
